image_processing_hallynny/__init__.py
image_processing_hallynny/processing/__init__.py
image_processing_hallynny/processing/combination.py
image_processing_hallynny/processing/transformation.py
image_processing_hallynny/utils/__init__.py
image_processing_hallynny/utils/io.py
image_processing_hallynny/utils/plot.py
image_processing_hallynny-0.0.1.dist-info/METADATA
image_processing_hallynny-0.0.1.dist-info/WHEEL
image_processing_hallynny-0.0.1.dist-info/top_level.txt
image_processing_hallynny-0.0.1.dist-info/RECORD
