Metadata-Version: 2.1
Name: image-processing-hallynny
Version: 0.0.1
Summary: Image Processing Package using Skimage
Home-page: https://github.com/hallynnyh/DESAFIOS_DIO/tree/main/image_processing_hallynny
Author: Hallynnyh
License: UNKNOWN
Platform: UNKNOWN
Requires-Python: >=3.8
Requires-Dist: matplotlib
Requires-Dist: numpy
Requires-Dist: scikit-image>=0.16.1
